{"image":"python:3.9","code":"community","thumb":"https://osresource.grjky.com/image/9.png","course":"python333","description":"Python 是一种解释型语言： 这意味着开发过程中没有了编译这个环节。类似于PHP和Perl语言。Python 是交互式语言： 这意味着，您可以在一个 Python 提示符 ​>>>​后直接执行代码。Python 是面向对象语言: 这​意味着Python​支持面向对象的风格或代码封装在对象的编程技术。Python 是初学者的语言：Python 对初级程序员而言，是一种伟大的语言，它支持广泛的应用程序开发，从简单的文字处理到服务器再到游戏，它都可以胜任。","title":"Python3","type":"认证","key":"1707997271c0e001","dirs":[{"path":"/第一章","parent":"/","index":0,"title":"第一章","category":"chapter","type":"chapter","image":""},{"path":"/第一章/第1节","parent":"/第一章","index":0,"title":"第1节","category":"content","type":"text","image":"","detail":{"text":"index.md","video":"index.mp4"}},{"path":"/第二章","parent":"/","index":1,"title":"第二章","category":"chapter","type":"chapter","image":""},{"path":"/第二章/第1节","parent":"/第二章","index":0,"title":"第1节","category":"content","type":"video","image":"","detail":{"text":"index.md","video":"index.mp4"}}],"speed":"/第二章/第1节"}